netboxcli/__init__.py
netboxcli/circuits/__init__.py
netboxcli/circuits/circuit_types.py
netboxcli/circuits/circuits.py
netboxcli/circuits/provider_accounts.py
netboxcli/circuits/provider_networks.py
netboxcli/circuits/providers.py
netboxcli/client.py
netboxcli/connections/__init__.py
netboxcli/connections/cables.py
netboxcli/connections/wireless_links.py
netboxcli/core.py
netboxcli/customization/__init__.py
netboxcli/customization/custom_fields.py
netboxcli/customization/custom_links.py
netboxcli/customization/export_templates.py
netboxcli/customization/image_attachments.py
netboxcli/customization/reports.py
netboxcli/customization/saved_filters.py
netboxcli/customization/scripts.py
netboxcli/customization/tags.py
netboxcli/devices/__init__.py
netboxcli/devices/console_ports.py
netboxcli/devices/console_server_ports.py
netboxcli/devices/device_types.py
netboxcli/devices/devices.py
netboxcli/devices/devices_roles.py
netboxcli/devices/front_ports.py
netboxcli/devices/interfaces.py
netboxcli/devices/inventory_items.py
netboxcli/devices/inventory_items_roles.py
netboxcli/devices/manufacturers.py
netboxcli/devices/modules.py
netboxcli/devices/modules_bays.py
netboxcli/devices/modules_types.py
netboxcli/devices/platforms.py
netboxcli/devices/power_outlets.py
netboxcli/devices/power_ports.py
netboxcli/devices/rear_ports.py
netboxcli/devices/virtual_chassis.py
netboxcli/devices/virtual_chassis_contexts.py
netboxcli/ipam/__init__.py
netboxcli/ipam/aggregates.py
netboxcli/ipam/asn_ranges.py
netboxcli/ipam/asns.py
netboxcli/ipam/fhrp_groups.py
netboxcli/ipam/ip_addresses.py
netboxcli/ipam/ip_ranges.py
netboxcli/ipam/prefix_roles.py
netboxcli/ipam/prefixes.py
netboxcli/ipam/rirs.py
netboxcli/ipam/router_targets.py
netboxcli/ipam/services.py
netboxcli/ipam/services_templates.py
netboxcli/ipam/vlan_groups.py
netboxcli/ipam/vlans.py
netboxcli/ipam/vrfs.py
netboxcli/operations/__init__.py
netboxcli/operations/data_sources.py
netboxcli/operations/jobs.py
netboxcli-1.2.0.dist-info/LICENSE
netboxcli-1.2.0.dist-info/METADATA
netboxcli-1.2.0.dist-info/WHEEL
netboxcli-1.2.0.dist-info/RECORD
