Metadata-Version: 2.1
Name: netboxcli
Version: 1.2.0
Summary: A Python package to interact with the NetBox API.
License: MIT
Author: kaio Guilherme 
Author-email: kaioguilherme444@gmail.com
Requires-Python: >=3.12,<4.0
Classifier: Development Status :: 5 - Production/Stable
Classifier: Intended Audience :: Developers
Classifier: License :: OSI Approved :: MIT License
Classifier: Operating System :: OS Independent
Classifier: Programming Language :: Python :: 3
Classifier: Programming Language :: Python :: 3.12
Classifier: Topic :: Software Development :: Libraries
Classifier: Topic :: System :: Networking
Requires-Dist: requests (>=2.31.0,<3.0.0)
Project-URL: Bug Tracker, https://github.com/Kaioguilherme1/netbox-client/issues
Project-URL: Codigo, https://github.com/Kaioguilherme1/netbox-client
Project-URL: Documentation, https://netboxcli.readthedocs.io/pt/latest/client/
Project-URL: Homepage, https://netboxcli.readthedocs.io/pt/latest/
